copiedMultielo/__init__.py
copiedMultielo/_version.py
copiedMultielo/multielo.py
copiedMultielo/player_tracker.py
copiedMultielo/score_functions.py
copiedMultielo-0.3.1.dist-info/LICENSE
copiedMultielo-0.3.1.dist-info/METADATA
copiedMultielo-0.3.1.dist-info/WHEEL
copiedMultielo-0.3.1.dist-info/top_level.txt
copiedMultielo-0.3.1.dist-info/RECORD
